{"data": {"values": [{"Name": "amc p", "Miles_per_Gallon": 19.0}, {"Name": "amc a", "Miles_per_Gallon": 15.0}, {"Name": "ford ", "Miles_per_Gallon": 17.0}, {"Name": "trium", "Miles_per_Gallon": 35.0}, {"Name": "renau", "Miles_per_Gallon": 26.0}]}, "width": 200.0, "height": 400, "mark": "bar", "encoding": {"x": {"field": "Name", "type": "ordinal", "scale": {"type": "band", "paddingInner": 0}, "axis": {"labelAngle": -45.0}, "sort": null, "title": null, "band": 0.6}, "y": {"title": null, "field": "Miles_per_Gallon", "type": "quantitative", "axis": {"grid": false}}}}